spetlrtools/__init__.py
spetlrtools/manipulate_version.py
spetlrtools/requirements.py
spetlrtools/az_databricks_token/AuthLinkOpener.py
spetlrtools/az_databricks_token/__init__.py
spetlrtools/az_databricks_token/get_ad_access_token.py
spetlrtools/az_databricks_token/get_impersonation_authorization_code.py
spetlrtools/az_databricks_token/main.py
spetlrtools/az_databricks_token/server.py
spetlrtools/cli_install/__init__.py
spetlrtools/cli_install/defaults.py
spetlrtools/cli_install/install.py
spetlrtools/cli_install/latest.py
spetlrtools/cli_install/main.py
spetlrtools/cli_install/uninstall.py
spetlrtools/diagrams/DiagramMarkupLibraryParser.py
spetlrtools/diagrams/DrawioDiagramParser.py
spetlrtools/diagrams/Edge.py
spetlrtools/diagrams/HTMLStripper.py
spetlrtools/diagrams/__init__.py
spetlrtools/diagrams/main.py
spetlrtools/entry_points/__init__.py
spetlrtools/entry_points/task_entry_point_helper.py
spetlrtools/format/__init__.py
spetlrtools/format/validate_camelcased_cols.py
spetlrtools/helpers/ExtractEncodedBody.py
spetlrtools/helpers/ExtractEncodedBodyUC.py
spetlrtools/helpers/__init__.py
spetlrtools/helpers/get_difference_between_two_dfs.py
spetlrtools/helpers/module_helper.py
spetlrtools/test_job/RemoteLocation.py
spetlrtools/test_job/RunDetails.py
spetlrtools/test_job/__init__.py
spetlrtools/test_job/dbcli.py
spetlrtools/test_job/fetch.py
spetlrtools/test_job/main.py
spetlrtools/test_job/submit.py
spetlrtools/test_job/test_main.py
spetlrtools/testing/DataframeTestCase.py
spetlrtools/testing/TestHandle.py
spetlrtools/testing/TupleComparer.py
spetlrtools/testing/__init__.py
spetlrtools/time/TimeSequence.py
spetlrtools/time/__init__.py
spetlr_tools-0.1.72.dist-info/LICENSE
spetlr_tools-0.1.72.dist-info/METADATA
spetlr_tools-0.1.72.dist-info/WHEEL
spetlr_tools-0.1.72.dist-info/entry_points.txt
spetlr_tools-0.1.72.dist-info/top_level.txt
spetlr_tools-0.1.72.dist-info/RECORD
