Metadata-Version: 2.1
Name: spetlr-tools
Version: 0.1.72
Summary: Supplements to the python SPark ETL libRary (SPETLR) for Databricks.
Home-page: https://github.com/spetlr-org/spetlr-tools
Author: Spetlr.Org
Author-email: spetlr.org@gmail.com
Project-URL: Documentation, https://github.com/spetlr-org/spetlr-tools
Project-URL: Bug Reports, https://github.com/spetlr-org/spetlr-tools/issues
Project-URL: Source Code, https://github.com/spetlr-org/spetlr-tools
Keywords: databricks,pyspark,spetlr
Classifier: Development Status :: 2 - Pre-Alpha
Classifier: Intended Audience :: Developers
Classifier: Topic :: Software Development :: Build Tools
Classifier: Programming Language :: Python :: 3
Classifier: Programming Language :: Python :: 3.10
Classifier: Programming Language :: Python :: 3 :: Only
Classifier: License :: OSI Approved :: MIT License
Classifier: Operating System :: OS Independent
Requires-Python: >=3.10
License-File: LICENSE
Requires-Dist: spetlr
Requires-Dist: pyyaml
Requires-Dist: importlib-metadata
Requires-Dist: dateparser
Requires-Dist: pytest
Requires-Dist: packaging
Requires-Dist: requests
Requires-Dist: databricks-sdk
Provides-Extra: dev
Requires-Dist: check-manifest; extra == "dev"
